disaggregation/pandas_add_on.py
disaggregation/tests.py
disaggregation/variational_framework.py
disaggregation-0.6.0.dist-info/METADATA
disaggregation-0.6.0.dist-info/WHEEL
disaggregation-0.6.0.dist-info/top_level.txt
disaggregation-0.6.0.dist-info/RECORD
