Metadata-Version: 2.4
Name: disaggregation
Version: 0.6.0
Summary: Disaggregates in Pandas
Author: Nathaniel Rogalskyj
Author-email: nr282@cornell.edu
Classifier: Programming Language :: Python :: 3
Classifier: License :: OSI Approved :: MIT License
Classifier: Operating System :: OS Independent
Requires-Dist: requests
Requires-Dist: numpy>=1.20
Requires-Dist: pandas
Requires-Dist: scipy
Requires-Dist: coverage
Requires-Dist: matplotlib
Dynamic: author
Dynamic: author-email
Dynamic: classifier
Dynamic: requires-dist
Dynamic: summary
